[ {
  "id" : "DL01",
  "modelo" : "ModeloTest",
  "disponivel" : false,
  "registroDatalogger" : [ {
    "id" : "e4a378ef-ed02-4bdb-abd1-de1d871fc2dd",
    "temperatura" : 4.95,
    "rede" : true,
    "energia" : 13.3,
    "compressor" : true,
    "alarme" : false,
    "data_hora" : "2026-06-05T19:26:07.191654877"
  }, {
    "id" : "68eef814-f419-45e6-ac1e-9d342d8324fd",
    "temperatura" : 5.25,
    "rede" : true,
    "energia" : 13.3,
    "compressor" : true,
    "alarme" : false,
    "data_hora" : "2026-06-05T19:26:12.201512035"
  }, {
    "id" : "d08c9fcb-2133-46af-9e87-1cf2154189fd",
    "temperatura" : 5.65,
    "rede" : true,
    "energia" : 13.3,
    "compressor" : true,
    "alarme" : false,
    "data_hora" : "2026-06-05T19:26:17.205661262"
  }, {
    "id" : "7f961124-f38a-4369-a9a6-a3e9c9c2500b",
    "temperatura" : 5.95,
    "rede" : true,
    "energia" : 13.6,
    "compressor" : true,
    "alarme" : false,
    "data_hora" : "2026-06-05T19:26:22.210013908"
  }, {
    "id" : "232f8f60-c0eb-4750-9837-da3a1fc1c720",
    "temperatura" : 6.45,
    "rede" : true,
    "energia" : 13.3,
    "compressor" : true,
    "alarme" : false,
    "data_hora" : "2026-06-05T19:26:27.214894932"
  }, {
    "id" : "b84d6c9b-878b-4b06-a9ac-846d88fa3012",
    "temperatura" : 7.05,
    "rede" : true,
    "energia" : 13.3,
    "compressor" : true,
    "alarme" : false,
    "data_hora" : "2026-06-05T19:26:32.217811445"
  }, {
    "id" : "cb15445d-5c33-42ca-82aa-210e403ebb60",
    "temperatura" : 7.6,
    "rede" : true,
    "energia" : 13.3,
    "compressor" : true,
    "alarme" : false,
    "data_hora" : "2026-06-05T19:26:37.22246389"
  }, {
    "id" : "983b4113-40e1-4c96-9883-0b6373cb9681",
    "temperatura" : 8.200001,
    "rede" : true,
    "energia" : 13.3,
    "compressor" : true,
    "alarme" : false,
    "data_hora" : "2026-06-05T19:26:42.225568261"
  }, {
    "id" : "c94ae645-9d85-4ae8-96d6-1492aec62afa",
    "temperatura" : 8.8,
    "rede" : true,
    "energia" : 13.4,
    "compressor" : true,
    "alarme" : true,
    "data_hora" : "2026-06-05T19:26:47.229580389"
  }, {
    "id" : "f0035fbe-bcaa-43df-97dc-73eeac21abc6",
    "temperatura" : 9.45,
    "rede" : true,
    "energia" : 13.4,
    "compressor" : true,
    "alarme" : true,
    "data_hora" : "2026-06-05T19:26:52.235286713"
  }, {
    "id" : "b82a11ee-8332-4324-a2ca-a53df27f5a74",
    "temperatura" : 10.15,
    "rede" : true,
    "energia" : 13.4,
    "compressor" : true,
    "alarme" : true,
    "data_hora" : "2026-06-05T19:26:57.240168325"
  }, {
    "id" : "3ee1405f-678f-4445-b983-151c519b32fe",
    "temperatura" : 11.05,
    "rede" : true,
    "energia" : 13.4,
    "compressor" : true,
    "alarme" : true,
    "data_hora" : "2026-06-05T19:27:02.244832695"
  }, {
    "id" : "1a25ac36-de8b-46f7-8cea-0244822046d2",
    "temperatura" : 11.85,
    "rede" : true,
    "energia" : 13.4,
    "compressor" : true,
    "alarme" : true,
    "data_hora" : "2026-06-05T19:27:07.250215128"
  }, {
    "id" : "93d68eb6-8adb-452c-9191-c79d6569f8e1",
    "temperatura" : 12.75,
    "rede" : true,
    "energia" : 13.3,
    "compressor" : true,
    "alarme" : true,
    "data_hora" : "2026-06-05T19:27:12.25536708"
  }, {
    "id" : "5e427e14-e20a-4b80-88ee-4c5d4bf5233b",
    "temperatura" : 13.65,
    "rede" : true,
    "energia" : 13.3,
    "compressor" : true,
    "alarme" : true,
    "data_hora" : "2026-06-05T19:27:17.261097599"
  }, {
    "id" : "1b43eacb-9e99-4b1f-93de-82330980d944",
    "temperatura" : 14.5,
    "rede" : true,
    "energia" : 13.3,
    "compressor" : true,
    "alarme" : true,
    "data_hora" : "2026-06-05T19:27:22.268017816"
  }, {
    "id" : "da12eaaa-e6d2-4ad8-8ebb-8df4aa1c7d0a",
    "temperatura" : 15.299999,
    "rede" : true,
    "energia" : 13.4,
    "compressor" : true,
    "alarme" : true,
    "data_hora" : "2026-06-05T19:27:27.271337481"
  }, {
    "id" : "b01c1b56-0240-4d6e-97d8-145a29a3486c",
    "temperatura" : 16.05,
    "rede" : true,
    "energia" : 14.7,
    "compressor" : true,
    "alarme" : true,
    "data_hora" : "2026-06-05T19:27:32.272760527"
  }, {
    "id" : "5bb869f8-db0b-4d59-805e-59d096e362f3",
    "temperatura" : 16.85,
    "rede" : true,
    "energia" : 13.4,
    "compressor" : true,
    "alarme" : true,
    "data_hora" : "2026-06-05T19:27:37.27638935"
  }, {
    "id" : "48091cb3-4873-4f60-a59e-242225e63e86",
    "temperatura" : 17.6,
    "rede" : true,
    "energia" : 13.3,
    "compressor" : true,
    "alarme" : true,
    "data_hora" : "2026-06-05T19:27:42.281085469"
  }, {
    "id" : "37926b80-9a81-4880-a791-6efdb2427407",
    "temperatura" : 18.3,
    "rede" : true,
    "energia" : 13.3,
    "compressor" : true,
    "alarme" : true,
    "data_hora" : "2026-06-05T19:27:47.287698494"
  }, {
    "id" : "2b936313-d834-4a9b-9d81-d47a47f1d1c8",
    "temperatura" : 18.95,
    "rede" : true,
    "energia" : 13.6,
    "compressor" : true,
    "alarme" : true,
    "data_hora" : "2026-06-05T19:27:52.291248059"
  }, {
    "id" : "24b0491d-f54a-44a7-aba1-71b1d14ef284",
    "temperatura" : 19.6,
    "rede" : true,
    "energia" : 13.3,
    "compressor" : true,
    "alarme" : true,
    "data_hora" : "2026-06-05T19:27:57.294654654"
  }, {
    "id" : "9c5cc716-53a3-44fc-a78c-7214049cd578",
    "temperatura" : 20.150002,
    "rede" : true,
    "energia" : 13.4,
    "compressor" : true,
    "alarme" : true,
    "data_hora" : "2026-06-05T19:28:02.299891727"
  }, {
    "id" : "c07dc45d-51e6-472e-aedf-c97166a726a6",
    "temperatura" : 20.6,
    "rede" : true,
    "energia" : 14.5,
    "compressor" : true,
    "alarme" : true,
    "data_hora" : "2026-06-05T19:28:07.30372508"
  }, {
    "id" : "5d234530-fb69-473c-9926-b26ce3118397",
    "temperatura" : 21.25,
    "rede" : true,
    "energia" : 13.4,
    "compressor" : true,
    "alarme" : true,
    "data_hora" : "2026-06-05T19:28:12.305252437"
  }, {
    "id" : "9665df58-f600-489c-9c03-37c856073fc4",
    "temperatura" : 21.7,
    "rede" : true,
    "energia" : 13.3,
    "compressor" : true,
    "alarme" : true,
    "data_hora" : "2026-06-05T19:28:17.308881386"
  }, {
    "id" : "c627e2bc-f0ff-42b5-9c83-5e7365fd14d8",
    "temperatura" : 22.150002,
    "rede" : true,
    "energia" : 13.3,
    "compressor" : true,
    "alarme" : true,
    "data_hora" : "2026-06-05T19:28:22.311606737"
  }, {
    "id" : "5432e1ff-a4b3-49d4-940f-0c3397d86cf4",
    "temperatura" : 22.6,
    "rede" : true,
    "energia" : 13.4,
    "compressor" : true,
    "alarme" : true,
    "data_hora" : "2026-06-05T19:28:27.314670868"
  }, {
    "id" : "dfb1b6f7-0a6e-4107-add5-2a27f5dbda6b",
    "temperatura" : 23.0,
    "rede" : true,
    "energia" : 13.3,
    "compressor" : true,
    "alarme" : true,
    "data_hora" : "2026-06-05T19:28:32.320396718"
  }, {
    "id" : "65331e28-3c48-48a2-965d-d1fa993eba56",
    "temperatura" : 23.35,
    "rede" : true,
    "energia" : 13.4,
    "compressor" : true,
    "alarme" : true,
    "data_hora" : "2026-06-05T19:28:37.323440679"
  }, {
    "id" : "1cd0e101-7ab5-4385-b7fc-d395f1e09c17",
    "temperatura" : 23.65,
    "rede" : true,
    "energia" : 13.4,
    "compressor" : true,
    "alarme" : true,
    "data_hora" : "2026-06-05T19:28:42.327885926"
  }, {
    "id" : "91f10304-0002-4c9d-baca-f8f529d48585",
    "temperatura" : 24.0,
    "rede" : true,
    "energia" : 13.3,
    "compressor" : true,
    "alarme" : true,
    "data_hora" : "2026-06-05T19:28:47.332773466"
  }, {
    "id" : "b49b1332-c35a-40b8-9fc9-9ef853bd4820",
    "temperatura" : 24.35,
    "rede" : true,
    "energia" : 13.5,
    "compressor" : true,
    "alarme" : true,
    "data_hora" : "2026-06-05T19:28:52.337406564"
  }, {
    "id" : "496c47d9-6752-49d0-9f6f-0356d8948f12",
    "temperatura" : 24.55,
    "rede" : true,
    "energia" : 13.3,
    "compressor" : true,
    "alarme" : true,
    "data_hora" : "2026-06-05T19:28:57.341516477"
  }, {
    "id" : "4438f4c5-c87f-4320-8533-d7b6f90eabc5",
    "temperatura" : 24.85,
    "rede" : true,
    "energia" : 13.3,
    "compressor" : true,
    "alarme" : true,
    "data_hora" : "2026-06-05T19:29:02.345467872"
  }, {
    "id" : "ba479afb-b51a-4559-a655-2723dfba3e68",
    "temperatura" : 25.15,
    "rede" : true,
    "energia" : 13.4,
    "compressor" : true,
    "alarme" : true,
    "data_hora" : "2026-06-05T19:29:07.350371725"
  }, {
    "id" : "af1032b1-6ed8-4651-af28-107b0de03522",
    "temperatura" : 25.35,
    "rede" : true,
    "energia" : 13.4,
    "compressor" : true,
    "alarme" : true,
    "data_hora" : "2026-06-05T19:29:12.354552949"
  }, {
    "id" : "77af44fe-01fb-4a3c-b4f7-b32174959859",
    "temperatura" : 25.55,
    "rede" : true,
    "energia" : 13.3,
    "compressor" : true,
    "alarme" : true,
    "data_hora" : "2026-06-05T19:29:17.357480232"
  }, {
    "id" : "f990687c-a3c4-4575-8227-bbc5c7419544",
    "temperatura" : 25.8,
    "rede" : true,
    "energia" : 13.4,
    "compressor" : true,
    "alarme" : true,
    "data_hora" : "2026-06-05T19:29:22.358866906"
  }, {
    "id" : "fdea32fa-73c1-4d0c-b502-c2be842c97d8",
    "temperatura" : 25.85,
    "rede" : true,
    "energia" : 13.3,
    "compressor" : true,
    "alarme" : true,
    "data_hora" : "2026-06-05T19:29:27.362789313"
  }, {
    "id" : "e4679f0a-2f85-445d-bb1e-39ba1447d137",
    "temperatura" : 26.15,
    "rede" : true,
    "energia" : 13.4,
    "compressor" : true,
    "alarme" : true,
    "data_hora" : "2026-06-05T19:29:32.36438021"
  }, {
    "id" : "15559152-dfe7-4b4c-9799-2f98a01a9cba",
    "temperatura" : 26.35,
    "rede" : true,
    "energia" : 13.3,
    "compressor" : true,
    "alarme" : true,
    "data_hora" : "2026-06-05T19:29:37.36664479"
  }, {
    "id" : "0f7bcfc2-c33a-431f-9482-08fcbb7b3242",
    "temperatura" : 26.5,
    "rede" : true,
    "energia" : 13.3,
    "compressor" : true,
    "alarme" : true,
    "data_hora" : "2026-06-05T19:29:42.369182523"
  }, {
    "id" : "7e36227d-af33-4f28-96ca-f670c1cb0ceb",
    "temperatura" : 26.75,
    "rede" : true,
    "energia" : 13.3,
    "compressor" : true,
    "alarme" : true,
    "data_hora" : "2026-06-05T19:29:47.372596757"
  }, {
    "id" : "0c5eeb62-eca9-4b40-998f-a940182dd24d",
    "temperatura" : 26.8,
    "rede" : true,
    "energia" : 13.4,
    "compressor" : true,
    "alarme" : true,
    "data_hora" : "2026-06-05T19:29:52.376369607"
  }, {
    "id" : "f16b7ad2-8af0-49b9-ac03-aae17756f172",
    "temperatura" : 26.95,
    "rede" : true,
    "energia" : 13.3,
    "compressor" : true,
    "alarme" : true,
    "data_hora" : "2026-06-05T19:29:57.379900221"
  }, {
    "id" : "aa12c390-2a94-4bed-9b54-d0e91ce04ec4",
    "temperatura" : 27.15,
    "rede" : true,
    "energia" : 13.3,
    "compressor" : true,
    "alarme" : true,
    "data_hora" : "2026-06-05T19:30:02.38430559"
  }, {
    "id" : "9dda42ef-4f6d-469f-84aa-9fcaf57665e8",
    "temperatura" : 27.25,
    "rede" : true,
    "energia" : 13.3,
    "compressor" : true,
    "alarme" : true,
    "data_hora" : "2026-06-05T19:30:07.387589802"
  }, {
    "id" : "374fa70b-100c-4a85-963b-068721202284",
    "temperatura" : 27.5,
    "rede" : true,
    "energia" : 13.3,
    "compressor" : true,
    "alarme" : true,
    "data_hora" : "2026-06-05T19:30:12.389579772"
  }, {
    "id" : "d26f75d8-1e05-4b63-8723-715741ea9f16",
    "temperatura" : 27.5,
    "rede" : true,
    "energia" : 14.7,
    "compressor" : true,
    "alarme" : true,
    "data_hora" : "2026-06-05T19:30:17.39376843"
  } ]
} ]